README.md
setup.py
ga2/__init__.py
ga2/automation/__init__.py
ga2/automation/api.py
ga2/automation/automationHelper.py
ga2/automation/automationHelperEngine.py
ga2/automation/automationHelperImage.py
ga2/automation/automationHelperNative.py
ga2/automation/by.py
ga2/automation/uiconfig.py
ga2/cloud/__init__.py
ga2/cloud/platformHelper.py
ga2/cloud/reporter.py
ga2/cloud/httptools/__init__.py
ga2/cloud/httptools/command.py
ga2/cloud/httptools/errorhandler.py
ga2/cloud/httptools/exceptions.py
ga2/cloud/httptools/remoteConnection.py
ga2/cloud/httptools/utils.py
ga2/common/WebDriverException.py
ga2/common/WebDriverWait.py
ga2/common/__init__.py
ga2/common/cmdExecuter.py
ga2/common/imapUtf7.py
ga2/common/loggerConfig.py
ga2/common/rpcThread.py
ga2/common/singleton.py
ga2/common/socketClient.py
ga2/common/timeout.py
ga2/common/utils.py
ga2/common/wetestExceptions.py
ga2/device/__init__.py
ga2/device/device.py
ga2/device/deviceOrientation.py
ga2/device/screenShoter.py
ga2/device/android/__init__.py
ga2/device/android/adbProcess.py
ga2/device/android/androidDevice.py
ga2/device/android/defaultScreenShoter.py
ga2/device/android/inputHelper.py
ga2/device/android/uiauto/__init__.py
ga2/device/android/uiauto/uiautoManager.py
ga2/device/android/uiauto/uiautomator.py
ga2/device/iOS/__init__.py
ga2/device/iOS/defaultScreenShoter.py
ga2/device/iOS/iMobiledevice.py
ga2/device/iOS/iOSDevice.py
ga2/device/iOS/iProxyManager.py
ga2/device/iOS/wdaManager.py
ga2/device/iOS/wda/__init__.py
ga2/device/iOS/wda/xcui_element_types.py
ga2/engine/UE4Engine.py
ga2/engine/__init__.py
ga2/engine/element.py
ga2/engine/engine.py
ga2/engine/engineFactory.py
ga2/engine/protocol.py
ga2/engine/uielement.py
ga2/engine/unityEngine.py
ga2/uiimage/__init__.py
ga2/uiimage/cv2helper.py
ga2/uiimage/featurematcher.py
ga2/uiimage/imageMatcher.py
ga2/uiimage/tmplatematcher.py
ga2/uiimage/utils.py
gautomator2.egg-info/PKG-INFO
gautomator2.egg-info/SOURCES.txt
gautomator2.egg-info/dependency_links.txt
gautomator2.egg-info/requires.txt
gautomator2.egg-info/top_level.txt